enum_adt-0.0.2.dist-info/METADATA
enum_adt-0.0.2.dist-info/WHEEL
enum_adt-0.0.2.dist-info/licenses/LICENSE
enum_adt.py
enum_adt-0.0.2.dist-info/RECORD
