Metadata-Version: 2.1
Name: enum-adt
Version: 0.0.2
Summary: Enum Algebraic Data Types (ADTs) for Python
Author-Email: Frost Ming <me@frostming.com>
License: MIT
Classifier: Development Status :: 3 - Alpha
Classifier: Intended Audience :: Developers
Classifier: Programming Language :: Python :: 3
Classifier: Programming Language :: Python :: 3.8
Classifier: Programming Language :: Python :: 3.9
Classifier: Programming Language :: Python :: 3.10
Classifier: Programming Language :: Python :: 3.11
Classifier: Programming Language :: Python :: 3.12
Classifier: Programming Language :: Python :: 3 :: Only
Project-URL: Repository, https://github.com/frostming/enum-adt
Requires-Python: >=3.8
